[
    {
        "CHR": 1,
        "BP_MIN": 0,
        "BP_MAX": 248956422,
        "MAX_BP_ABS": 248956422
    },
    {
        "CHR": 2,
        "BP_MIN": 0,
        "BP_MAX": 242193529,
        "MAX_BP_ABS": 491149951
    },
    {
        "CHR": 3,
        "BP_MIN": 0,
        "BP_MAX": 198295559,
        "MAX_BP_ABS": 689445510
    },
    {
        "CHR": 4,
        "BP_MIN": 0,
        "BP_MAX": 190214555,
        "MAX_BP_ABS": 879660065
    },
    {
        "CHR": 5,
        "BP_MIN": 0,
        "BP_MAX": 181538259,
        "MAX_BP_ABS": 1061198324
    },
    {
        "CHR": 6,
        "BP_MIN": 0,
        "BP_MAX": 170805979,
        "MAX_BP_ABS": 1232004303
    },
    {
        "CHR": 7,
        "BP_MIN": 0,
        "BP_MAX": 159345973,
        "MAX_BP_ABS": 1391350276
    },
    {
        "CHR": 8,
        "BP_MIN": 0,
        "BP_MAX": 145138636,
        "MAX_BP_ABS": 1536488912
    },
    {
        "CHR": 9,
        "BP_MIN": 0,
        "BP_MAX": 138394717,
        "MAX_BP_ABS": 1674883629
    },
    {
        "CHR": 10,
        "BP_MIN": 0,
        "BP_MAX": 133797422,
        "MAX_BP_ABS": 1808681051
    },
    {
        "CHR": 11,
        "BP_MIN": 0,
        "BP_MAX": 135086622,
        "MAX_BP_ABS": 1943767673
    },
    {
        "CHR": 12,
        "BP_MIN": 0,
        "BP_MAX": 133275309,
        "MAX_BP_ABS": 2077042982
    },
    {
        "CHR": 13,
        "BP_MIN": 0,
        "BP_MAX": 114364328,
        "MAX_BP_ABS": 2191407310
    },
    {
        "CHR": 14,
        "BP_MIN": 0,
        "BP_MAX": 107043718,
        "MAX_BP_ABS": 2298451028
    },
    {
        "CHR": 15,
        "BP_MIN": 0,
        "BP_MAX": 101991189,
        "MAX_BP_ABS": 2400442217
    },
    {
        "CHR": 16,
        "BP_MIN": 0,
        "BP_MAX": 90338345,
        "MAX_BP_ABS": 2490780562
    },
    {
        "CHR": 17,
        "BP_MIN": 0,
        "BP_MAX": 83257441,
        "MAX_BP_ABS": 2574038003
    },
    {
        "CHR": 18,
        "BP_MIN": 0,
        "BP_MAX": 80373285,
        "MAX_BP_ABS": 2654411288
    },
    {
        "CHR": 19,
        "BP_MIN": 0,
        "BP_MAX": 58617616,
        "MAX_BP_ABS": 2713028904
    },
    {
        "CHR": 20,
        "BP_MIN": 0,
        "BP_MAX": 64444167,
        "MAX_BP_ABS": 2777473071
    },
    {
        "CHR": 21,
        "BP_MIN": 0,
        "BP_MAX": 46709983,
        "MAX_BP_ABS": 2824183054
    },
    {
        "CHR": 22,
        "BP_MIN": 0,
        "BP_MAX": 50818468,
        "MAX_BP_ABS": 2875001522
    },
    {
        "CHR": 23,
        "BP_MIN": 0,
        "BP_MAX": 156040895,
        "MAX_BP_ABS": 3031042417
    },
    {
        "CHR": 24,
        "BP_MIN": 0,
        "BP_MAX": 57227415,
        "MAX_BP_ABS": 3088269832
    }
]